wiseprophet/__init__.py
wiseprophet/common.py
wiseprophet/hdfsService.py
wiseprophet/wpType.py
wiseprophet/config/__init__.py
wiseprophet/config/wp.py
wiseprophet-0.0.10.dist-info/METADATA
wiseprophet-0.0.10.dist-info/WHEEL
wiseprophet-0.0.10.dist-info/top_level.txt
wiseprophet-0.0.10.dist-info/RECORD
